[{"backgrounds":[],"bigIllustrations":[],"effects":[],"fullText":"전속 계약 다음엔 정확히 어떻게 후원하면 되죠?　","illustrationsL":[{"Key":0,"Value":[110]}],"illustrationsR":[],"markerPositionList":[{"x":-465,"y":95,"z":0},{"x":-465,"y":95,"z":0}],"names":[{"Key":0,"Value":["주인공"]}],"smallIllustrations":[],"textType":2},{"backgrounds":[],"bigIllustrations":[],"effects":[],"fullText":"이번엔 예외이지만\r\n보통은 던전을 공략할 때 다른 모험가들과 경쟁해야 하네.\r\n　","illustrationsL":[{"Key":0,"Value":[0]}],"illustrationsR":[],"markerPositionList":[{"x":-465,"y":95,"z":0},{"x":-465,"y":95,"z":0}],"names":[{"Key":0,"Value":["할배"]}],"smallIllustrations":[],"textType":2},{"backgrounds":[],"bigIllustrations":[],"effects":[],"fullText":"보스를 공략한 모험가는 던전에 영원히 이름을 남길 수 있다네.\r\n하지만 그 이름을 남기는 건 한 명 뿐이지.\r\n　","illustrationsL":[],"illustrationsR":[],"markerPositionList":[],"names":[],"smallIllustrations":[],"textType":2},{"backgrounds":[],"bigIllustrations":[],"effects":[],"fullText":"할배 뭘 좀 알긴 하나본데.　","illustrationsL":[{"Key":0,"Value":[110]}],"illustrationsR":[],"markerPositionList":[{"x":-465,"y":95,"z":0},{"x":-465,"y":95,"z":0}],"names":[{"Key":0,"Value":["주인공"]}],"smallIllustrations":[],"textType":0},{"backgrounds":[],"bigIllustrations":[],"effects":[],"fullText":"그럼 계약을 맺은 일선 모험가를 밀어줘야 되겠네요.　","illustrationsL":[],"illustrationsR":[],"markerPositionList":[],"names":[],"smallIllustrations":[],"textType":2},{"backgrounds":[],"bigIllustrations":[],"effects":[],"fullText":"그렇지. 아이템을 후원해 강하게 만들어주면 된다네.\r\n자네의 후원이 모험가의 승리로\r\n승리가 홍보효과로 돌아오는 셈이지.\r\n　","illustrationsL":[{"Key":0,"Value":[0]}],"illustrationsR":[],"markerPositionList":[{"x":-465,"y":95,"z":0},{"x":-465,"y":95,"z":0}],"names":[{"Key":0,"Value":["할배"]}],"smallIllustrations":[],"textType":2},{"backgrounds":[],"bigIllustrations":[],"effects":[],"fullText":"육성 버튼을 누르고 왼쪽 메뉴에서 아이템을 누르게.\r\n그럼 아이템 구매창이 나올게야.\r　","illustrationsL":[],"illustrationsR":[],"markerPositionList":[],"names":[],"smallIllustrations":[],"textType":2},{"backgrounds":[],"bigIllustrations":[],"effects":[],"fullText":"괜찮은 아이템 하나 맞춰주게나.\r\n구매하면 장착은 알아서 된다네.\r\n　","illustrationsL":[],"illustrationsR":[],"markerPositionList":[],"names":[],"smallIllustrations":[],"textType":2}]